loadstructure/__init__.py
loadstructure/config_node.py
loadstructure/main.py
loadstructure/utils/helper.py
loadstructure-0.2.2.dist-info/licenses/LICENSE
loadstructure-0.2.2.dist-info/METADATA
loadstructure-0.2.2.dist-info/WHEEL
loadstructure-0.2.2.dist-info/top_level.txt
loadstructure-0.2.2.dist-info/RECORD
