Metadata-Version: 2.4
Name: loadstructure
Version: 0.2.2
Summary: A versatile Python library for loading and managing configuration files (JSON, YAML, XML, TOML, and INI/DEF-style) with attribute-style access, merging capabilities.
Author-email: Anmol Kumar <ask995844@gmail.com>
License: MIT License
Project-URL: Homepage, https://github.com/TechRuler/loadstructure
Requires-Python: >=3.13
License-File: LICENSE
Requires-Dist: pyyaml>=6.0.3
Requires-Dist: toml>=0.10.2
Requires-Dist: xmltodict>=1.0.2
Dynamic: license-file
